rockman/__init__.py
rockman/__main__.py
rockman/config/__init__.py
rockman/config/settings.py
rockman/features/__init__.py
rockman/features/django.py
rockman/features/react.py
rockman/features/redux_toolkit.py
rockman/features/rockman.py
rockman/helpers/__init__.py
rockman/helpers/python_helper.py
rockman/helpers/redux_helper.py
rockman/templates/__init__.py
rockman/templates/angular/__init__.py
rockman/templates/django/__init__.py
rockman/templates/react/__init__.py
rockman/templates/react/redux_thunk/__init__.py
rockman/templates/react/redux_thunk/action_methods.py
rockman/templates/react/redux_thunk/blueprints.py
rockman/templates/react/redux_thunk/reducer_methods.py
rockman/templates/react/redux_thunk/types.py
rockman/templates/react/redux_thunk/types_methods.py
rockman/templates/react/redux_toolkit/__init__.py
rockman/templates/react/redux_toolkit/components/__init__.py
rockman/templates/react/redux_toolkit/components/filters/__init__.py
rockman/templates/react/redux_toolkit/components/tables/__init__.py
rockman/templates/react/redux_toolkit/services/__init__.py
rockman/templates/vue/__init__.py
rockman/util/__init__.py
rockman/util/console.py
rockman/util/cover.py
rockman/util/text_generator.py
rockman-1.0.6.dist-info/LICENSE
rockman-1.0.6.dist-info/METADATA
rockman-1.0.6.dist-info/WHEEL
rockman-1.0.6.dist-info/entry_points.txt
rockman-1.0.6.dist-info/top_level.txt
rockman-1.0.6.dist-info/RECORD
