Metadata-Version: 2.1
Name: rockman
Version: 1.0.6
Summary: automatic code generator using python
Author: Acid Jelly
Author-email: jhospinal@acidjelly.com
Keywords: python,react,django,redux,generator,code
Classifier: Development Status :: 1 - Planning
Classifier: Intended Audience :: Developers
Classifier: Programming Language :: Python :: 3
Classifier: Operating System :: Unix
Classifier: Operating System :: MacOS :: MacOS X
Classifier: Operating System :: Microsoft :: Windows
License-File: LICENSE
Requires-Dist: typer
Requires-Dist: inquirer
